nonebot_plugin_buff/__init__.py
nonebot_plugin_buff/config.py
nonebot_plugin_buff-0.2.1.dist-info/METADATA
nonebot_plugin_buff-0.2.1.dist-info/WHEEL
nonebot_plugin_buff-0.2.1.dist-info/RECORD
