Metadata-Version: 2.1
Name: nonebot-plugin-buff
Version: 0.2.1
Summary: 实时爬取BUFF饰品价格
License: MIT
Author: Sydrr0
Author-email: 2562312527@qq.com
Requires-Python: >=3.8,<4.0
Classifier: License :: OSI Approved :: MIT License
Classifier: Programming Language :: Python :: 3
Classifier: Programming Language :: Python :: 3.8
Classifier: Programming Language :: Python :: 3.9
Classifier: Programming Language :: Python :: 3.10
Classifier: Programming Language :: Python :: 3.11
Requires-Dist: bs4 (>=0.0.1,<0.0.2)
Requires-Dist: httpx (>=0.24.1,<0.25.0)
Requires-Dist: nonebot2 (>=2.0.1,<3.0.0)
